pg_bulk_ingest/__init__.py
pg_bulk_ingest/py.typed
pg_bulk_ingest-0.0.57.dist-info/METADATA
pg_bulk_ingest-0.0.57.dist-info/WHEEL
pg_bulk_ingest-0.0.57.dist-info/licenses/LICENSE
pg_bulk_ingest-0.0.57.dist-info/RECORD
